tily/__init__.py
tily/__main__.py
tily/handlers.py
tily/models.py
tily/prediction.py
tily/tiff.py
tily-0.0.8.dist-info/LICENSE
tily-0.0.8.dist-info/METADATA
tily-0.0.8.dist-info/WHEEL
tily-0.0.8.dist-info/entry_points.txt
tily-0.0.8.dist-info/top_level.txt
tily-0.0.8.dist-info/RECORD
