Metadata-Version: 2.1
Name: tily
Version: 0.0.8
Summary: Tumor-infiltrating lymphocytes prediction based on Whole Slide Imaging.
Home-page: https://github.com/kandabarau/tily
Author: Sergey Kandabarau
Author-email: kandabarau@gmail.com
License: BSD
Project-URL: Bug Tracker, https://github.com/kandabarau/tily/issues
Platform: UNKNOWN
Classifier: Intended Audience :: Information Technology
Classifier: Intended Audience :: Science/Research
Classifier: License :: OSI Approved :: MIT License
Classifier: Programming Language :: Python :: 3
Classifier: Programming Language :: Python :: 3.7
Classifier: Programming Language :: Python :: 3.8
Classifier: Programming Language :: Python :: 3.9
Requires-Python: >=3.7, <=3.10
License-File: LICENSE
Requires-Dist: about-time (>=3.1.1)
Requires-Dist: absl-py (>=1.0.0)
Requires-Dist: alive-progress (>=2.1.0)
Requires-Dist: astor (>=0.8.1)
Requires-Dist: attrs (>=21.2.0)
Requires-Dist: certifi (>=2021.10.8)
Requires-Dist: charset-normalizer (>=2.0.9)
Requires-Dist: gast (>=0.2.2)
Requires-Dist: google-pasta (>=0.2.0)
Requires-Dist: grapheme (>=0.6.0)
Requires-Dist: grpcio (>=1.42.0)
Requires-Dist: h5py (>=2.10.0)
Requires-Dist: idna (>=3.3)
Requires-Dist: imagecodecs (>=2021.11.20)
Requires-Dist: importlib-metadata (>=4.8.2)
Requires-Dist: iniconfig (>=1.1.1)
Requires-Dist: keras-applications (>=1.0.8)
Requires-Dist: keras-preprocessing (>=1.1.2)
Requires-Dist: markdown (>=3.3.6)
Requires-Dist: numpy (>=1.17.3)
Requires-Dist: opt-einsum (>=3.3.0)
Requires-Dist: packaging (>=21.3)
Requires-Dist: pillow (>=8.4.0)
Requires-Dist: pluggy (>=1.0.0)
Requires-Dist: protobuf (>=3.19.1)
Requires-Dist: py (>=1.11.0)
Requires-Dist: pyparsing (>=3.0.6)
Requires-Dist: pytest (>=6.2.5)
Requires-Dist: requests (>=2.26.0)
Requires-Dist: six (>=1.16.0)
Requires-Dist: tensorboard (>=1.15.0)
Requires-Dist: tensorflow (>=1.15.5)
Requires-Dist: tensorflow-estimator (>=1.15.1)
Requires-Dist: tf-slim (>=1.1.0)
Requires-Dist: termcolor (>=1.1.0)
Requires-Dist: tifffile (>=2021.11.2)
Requires-Dist: toml (>=0.10.2)
Requires-Dist: typing-extensions (>=4.0.1)
Requires-Dist: urllib3 (>=1.26.7)
Requires-Dist: werkzeug (>=2.0.2)
Requires-Dist: wheel (>=0.37.0)
Requires-Dist: wrapt (>=1.13.3)
Requires-Dist: zipp (>=3.6.0)
